pg_components/__init__.py
pg_components/base.py
pg_components/caggs.py
pg_components/functions.py
pg_components/schedule.py
pg_components/tables.py
pg_components/utils.py
pg_components/views.py
pg_components-0.1.3.dist-info/METADATA
pg_components-0.1.3.dist-info/WHEEL
pg_components-0.1.3.dist-info/top_level.txt
pg_components-0.1.3.dist-info/RECORD
