Metadata-Version: 2.1
Name: pg-components
Version: 0.1.3
Author-email: Dan Kelleher <kelleherjdan@gmail.com>
Classifier: License :: OSI Approved :: MIT License
Classifier: Programming Language :: Python
Classifier: Programming Language :: Python :: 3
Requires-Dist: sqlalchemy >=2.0.0
Requires-Dist: ezloggers
Provides-Extra: dev
Requires-Dist: black ; extra == 'dev'
Requires-Dist: pytest ; extra == 'dev'
